vscodeformer/__init__.py
vscodeformer/__main__.py
vscodeformer/align_trans.py
vscodeformer/codeformer_arch.py
vscodeformer/face_restoration_helper.py
vscodeformer/img_util.py
vscodeformer/matlab_cp2tform.py
vscodeformer/misc.py
vscodeformer/parsenet.py
vscodeformer/retinaface.py
vscodeformer/retinaface_net.py
vscodeformer/retinaface_utils.py
vscodeformer/vqgan_arch.py
vscodeformer/models/codeformer.pth
vscodeformer/models/detection_Resnet50_Final.pth
vscodeformer/models/mmod_human_face_detector-4cb19393.dat
vscodeformer/models/parsing_parsenet.pth
vscodeformer/models/shape_predictor_5_face_landmarks-c4b1e980.dat
vscodeformer-1.0.1.dist-info/METADATA
vscodeformer-1.0.1.dist-info/WHEEL
vscodeformer-1.0.1.dist-info/licenses/LICENSE
vscodeformer-1.0.1.dist-info/RECORD
