Metadata-Version: 2.1
Name: vscodeformer
Version: 1.0.1
Summary: CodeFormer function for VapourSynth
Project-URL: Homepage, https://github.com/HolyWu/vs-codeformer
Project-URL: Bug Tracker, https://github.com/HolyWu/vs-codeformer/issues
Author-email: HolyWu <holywu@gmail.com>
License: S-Lab License 1.0
License-File: LICENSE
Keywords: CodeFormer,VapourSynth
Classifier: Operating System :: OS Independent
Classifier: Programming Language :: Python :: 3.10
Classifier: Topic :: Multimedia :: Video
Requires-Python: >=3.10
Requires-Dist: numpy>=1.24.2
Requires-Dist: opencv-python>=4.7.0.72
Requires-Dist: requests>=2.28.2
Requires-Dist: torch>=1.13.1
Requires-Dist: torchvision>=0.14.1
Requires-Dist: tqdm>=4.65.0
Requires-Dist: vapoursynth>=55
